Metadata-Version: 2.1
Name: algo-fun-prime-number
Version: 0.1.0
Summary: Tell if a number is prime or not
Home-page: https://gitlab.com/ChristopheLagaillarde/prime_number
Author: Christophe Lagaillarde
Author-email: chrislag94@gmail.com
License: MIT
License-File: LICENSE
